emojifier/__init__.py
emojifier/generator.py
emojifier/data/__init__.py
emojifier/util/__init__.py
emojifier/util/emojify.py
emojifier/util/files.py
emojifier/util/text.py
emojifier-1.1.1.dist-info/LICENSE
emojifier-1.1.1.dist-info/METADATA
emojifier-1.1.1.dist-info/WHEEL
emojifier-1.1.1.dist-info/top_level.txt
emojifier-1.1.1.dist-info/RECORD
