Metadata-Version: 2.1
Name: emojifier
Version: 1.1.1
Summary: Emojifier is a module for emojifying text
Home-page: UNKNOWN
Author: MakufonSkifto
License: UNKNOWN
Project-URL: Issue tracker, https://github.com/MakufonSkifto/Emojifier/issues
Project-URL: Source, https://github.com/MakufonSkifto/Emojifier
Keywords: emoji emojifyer emojipasta pasta reddit emojis emojify emojifier
Platform: UNKNOWN
Classifier: Programming Language :: Python :: 3
Classifier: Programming Language :: Python :: 3.5
Classifier: Programming Language :: Python :: 3.6
Classifier: Programming Language :: Python :: 3.7
Classifier: Programming Language :: Python :: 3.8
Classifier: Programming Language :: Python :: 3.9
Classifier: License :: OSI Approved :: GNU General Public License v3 (GPLv3)
Requires-Python: >=3.5
Requires-Dist: emoji
